aiwolf_nlp_json_converter/__init__.py
aiwolf_nlp_json_converter/converter.py
aiwolf_nlp_json_converter/gameInfo.py
aiwolf_nlp_json_converter/gameSetting.py
aiwolf_nlp_json_converter/talkHistory.py
aiwolf_nlp_json_converter/whisperHistory.py
aiwolf_nlp_json_converter-0.3.0.dist-info/METADATA
aiwolf_nlp_json_converter-0.3.0.dist-info/WHEEL
aiwolf_nlp_json_converter-0.3.0.dist-info/licenses/LICENSE
aiwolf_nlp_json_converter-0.3.0.dist-info/RECORD
