Metadata-Version: 2.3
Name: aiwolf-nlp-json-converter
Version: 0.3.0
Summary: aiwolf-nlp-json-converter
Project-URL: Homepage, https://aiwolf.org
Author-email: aiwolfdial <aiwolf@kanolab.net>, nwatanabe <nwatanabe@kanolab.net>
Maintainer-email: aiwolfdial <aiwolf@kanolab.net>, nwatanabe <nwatanabe@kanolab.net>
License: MIT License
Keywords: aiwolf
Requires-Python: >=3.8
Requires-Dist: aiwolf-nlp-common>=0.2.1
